pays/__init__.py
pays/commandException.py
pays/drapeau.py
pays/pays.py
pays/selectexcption.py
pays/valueereur.py
py_pays-1.0.3.dist-info/LICENCE
py_pays-1.0.3.dist-info/METADATA
py_pays-1.0.3.dist-info/WHEEL
py_pays-1.0.3.dist-info/top_level.txt
py_pays-1.0.3.dist-info/RECORD
